[
  {
    "continent_cd": "40",
    "continent_eng_nm": "Middle East",
    "continent_nm": "중동",
    "country_eng_nm": "Yemen",
    "country_iso_alp2": "YE",
    "country_nm": "예멘",
    "dang_map_download_url": "https://www.0404.go.kr/imgsrc.mofa?atch_file_id=COUNTRY_294&file_sn=3",
    "flag_download_url": "https://opendata.mofa.go.kr:8444/fileDownload/images/country_images/flags/159/20241010_172819613.png",
    "map_download_url": "https://opendata.mofa.go.kr:8444/fileDownload/images/country_images/maps/159/20220318_170906908.png",
    "wrt_dt": "2024-08-01",
    "address": "P.O. Box: 5005, House No.4 (off Iran Street), Hadda Area, Sanaa, Republic of Yemen",
    "email": "yemen@mofa.go.kr",
    "representative_number": "(966) 11-488-2211",
    "emergency_contact": "(966) 53-717-8300, 55-376-9538",
    "jurisdiction": null,
    "emergency_services": {
      "police": null,
      "fire": null,
      "emergency": null,
      "traffic_police": null
    },
    "medical_contact": "ㅇ 예멘은 국가의료보험제도가 없어, 진료비가 매우 비싸고 병원과 의사는 선지불을 요구하는 경우가 많습니다.<br>\r\nㅇ \"Yemen German Hospital\"과 같은 선진국 수준에 가까운 의료시설은 오로지 사나와 아덴 정도에만 존재하고 대도시와 떨어진 곳은 현대적인 의료시설이 없으며, 구급차 서비스가 되지 않습니다.<br>\r\nㅇ 약품은 약국에서 처방전 없이 구입할 수 있으며, 일부 처방약품은 구할 수 없는 상황을 대비하여 체류하는 동안 필요한 처방약품을 충분히 지참하는 것이 바람직합니다.<br>"
  }
]